hub/__init__.py
hub/_version.py
hub/compression.py
hub/constants.py
hub/htype.py
hub/api/__init__.py
hub/api/dataset.py
hub/api/info.py
hub/api/read.py
hub/api/tests/__init__.py
hub/api/tests/test_agreement.py
hub/api/tests/test_api.py
hub/api/tests/test_api_with_compression.py
hub/api/tests/test_chunk_sizes.py
hub/api/tests/test_dataset.py
hub/api/tests/test_grayscale.py
hub/api/tests/test_hosted_datasets.py
hub/api/tests/test_info.py
hub/api/tests/test_json.py
hub/api/tests/test_meta.py
hub/api/tests/test_pickle.py
hub/api/tests/test_readonly.py
hub/api/tests/test_text.py
hub/api/tests/test_update_samples.py
hub/api/tests/test_video.py
hub/auto/__init__.py
hub/auto/tests/__init__.py
hub/auto/tests/test_ingestion.py
hub/auto/tests/test_kaggle.py
hub/auto/unstructured/__init__.py
hub/auto/unstructured/base.py
hub/auto/unstructured/image_classification.py
hub/auto/unstructured/kaggle.py
hub/cli/__init__.py
hub/cli/auth.py
hub/cli/commands.py
hub/cli/list_datasets.py
hub/cli/test_cli.py
hub/client/__init__.py
hub/client/client.py
hub/client/config.py
hub/client/log.py
hub/client/test_client.py
hub/client/utils.py
hub/core/__init__.py
hub/core/chunk.py
hub/core/chunk_engine.py
hub/core/compression.py
hub/core/fast_forwarding.py
hub/core/io.py
hub/core/ipc.py
hub/core/lock.py
hub/core/sample.py
hub/core/serialize.py
hub/core/tensor.py
hub/core/compute/__init__.py
hub/core/compute/process.py
hub/core/compute/provider.py
hub/core/compute/ray.py
hub/core/compute/serial.py
hub/core/compute/thread.py
hub/core/dataset/__init__.py
hub/core/dataset/dataset.py
hub/core/dataset/hub_cloud_dataset.py
hub/core/index/__init__.py
hub/core/index/index.py
hub/core/index/tests/test_index.py
hub/core/meta/__init__.py
hub/core/meta/dataset_meta.py
hub/core/meta/meta.py
hub/core/meta/tensor_meta.py
hub/core/meta/encode/__init__.py
hub/core/meta/encode/base_encoder.py
hub/core/meta/encode/byte_positions.py
hub/core/meta/encode/chunk_id.py
hub/core/meta/encode/shape.py
package_hub_test-2.1.40.dist-info/LICENSE
package_hub_test-2.1.40.dist-info/METADATA
package_hub_test-2.1.40.dist-info/WHEEL
package_hub_test-2.1.40.dist-info/entry_points.txt
package_hub_test-2.1.40.dist-info/top_level.txt
package_hub_test-2.1.40.dist-info/RECORD
