Metadata-Version: 2.1
Name: package-hub-test
Version: 2.1.40
Summary: demo
Home-page: UNKNOWN
Author: activeloop.ai
Author-email: support@activeloop.ai
License: UNKNOWN
Project-URL: Documentation, https://demo.ai/
Project-URL: Source, https://github.com/gkr-bot/Hub
Platform: UNKNOWN
Requires-Dist: numpy
Requires-Dist: pillow (==8.3.2)
Requires-Dist: boto3
Requires-Dist: boto3-stubs[essential]
Requires-Dist: google-cloud-storage (~=1.42.0)
Requires-Dist: google-auth (~=2.0.1)
Requires-Dist: google-auth-oauthlib (~=0.4.5)
Requires-Dist: pathos
Requires-Dist: humbug (>=0.2.6)
Requires-Dist: types-requests
Requires-Dist: types-click
Requires-Dist: tqdm
Requires-Dist: lz4
Requires-Dist: typing-extensions (>=3.10.0.0)
Requires-Dist: numcodecs (~=0.7.3)
Requires-Dist: miniaudio (~=1.44)
Requires-Dist: hub-shm ; python_version < "3.8" and python_version >= "3.6"
Requires-Dist: pickle5 (>=0.0.11) ; python_version < "3.8" and python_version >= "3.6"
